[
    [
        {
            "id": "5qHYXcVvc9xsFB2uH7GpMN",
            "name": "Kokomo",
            "artists": "The Beach Boys"
        },
        {
            "id": "5ayicakbGkOJJLW26HJ8Rg",
            "name": "Our House",
            "artists": "Madness"
        },
        {
            "id": "1K1nzhbKCNmrNXi9B07mPF",
            "name": "Forever In Blue Jeans",
            "artists": "Neil Diamond"
        }
    ],
    [
        {
            "id": "4SDywo3ykB2PEthjXvo1UP",
            "name": "I Put A Spell On You",
            "artists": "Creedence Clearwater Revival"
        },
        {
            "id": "2JhJOPGvtqMpj5RQC8cIYf",
            "name": "Perfect Strangers",
            "artists": "Deep Purple"
        },
        {
            "id": "4TIJ7zSBNejpoIPaWpWRKc",
            "name": "Rebel Yell",
            "artists": "Billy Idol"
        }
    ],
    [
        {
            "id": "3gdewACMIVMEWVbyb8O9sY",
            "name": "Rocket Man (I Think It's Going To Be A Long, Long Time)",
            "artists": "Elton John"
        },
        {
            "id": "5932kbyNt445gDTT2chRUS",
            "name": "One More Try - Remastered",
            "artists": "George Michael"
        },
        {
            "id": "1O3xlreuUsPlSJXUYZzTjs",
            "name": "Raspberry Beret - Extended 12\" Version",
            "artists": "Prince"
        }
    ],
    [
        {
            "id": "5E89Izp4YhPyNShoxiOJ1u",
            "name": "Rock & Roll Band",
            "artists": "Boston"
        },
        {
            "id": "69MwNXryg6NT1lV7buN7U7",
            "name": "Gone Shootin'",
            "artists": "AC/DC"
        },
        {
            "id": "2V8KvnD5LVeeDChMWEkSzC",
            "name": "Nothin' But A Good Time - Remastered 2006",
            "artists": "Poison"
        }
    ],
    [
        {
            "id": "1lCRw5FEZ1gPDNPzy1K4zW",
            "name": "We Are The Champions - Remastered 2011",
            "artists": "Queen"
        },
        {
            "id": "4yrM5BVyJzy5Ed4GPO6e8j",
            "name": "I Wanna Be Your Lover",
            "artists": "Prince"
        },
        {
            "id": "1ot6jEe4w4hYnsOPjd3xKQ",
            "name": "I'm So Excited",
            "artists": "The Pointer Sisters"
        }
    ],
    [
        {
            "id": "4DepmK7DEszV9c6Z39D9XA",
            "name": "Tin Soldier (USA AM Radio Version)",
            "artists": "Small Faces"
        },
        {
            "id": "3kcaix8VptngsWoYDTqEN2",
            "name": "The Story In Your Eyes",
            "artists": "The Moody Blues"
        },
        {
            "id": "6rovOdp3HgK1DeAMYDzoA7",
            "name": "Maggie May",
            "artists": "Rod Stewart"
        }
    ],
    [
        {
            "id": "2AVkArcfALVk2X8sfPRzya",
            "name": "Summer Nights - From “Grease”",
            "artists": "John Travolta"
        },
        {
            "id": "27cJHbsqx5idVLRZ4f5VsN",
            "name": "Crazy - James Michael Mix",
            "artists": "Alanis Morissette"
        },
        {
            "id": "5Hcl1reJnHIfJBbCcglaKR",
            "name": "The Lady In Red",
            "artists": "Chris de Burgh"
        }
    ],
    [
        {
            "id": "4jLv3tDBu8ww2R07DvL12s",
            "name": "Man On The Moon",
            "artists": "R.E.M."
        },
        {
            "id": "6gXrEUzibufX9xYPk3HD5p",
            "name": "Life in the Fast Lane - 2013 Remaster",
            "artists": "Eagles"
        },
        {
            "id": "1IqFh00G2kvvMm8pRMpehA",
            "name": "Me and Bobby McGee",
            "artists": "Janis Joplin"
        }
    ],
    [
        {
            "id": "3VYrW02CQhbkYAe4rpG297",
            "name": "The Show Must Go On - Remastered 2011",
            "artists": "Queen"
        },
        {
            "id": "6hTcuIQa0sxrrByu9wTD7s",
            "name": "Born to Run",
            "artists": "Bruce Springsteen"
        },
        {
            "id": "4S1VYqwfkLit9mKVY3MXoo",
            "name": "Forever Young",
            "artists": "Alphaville"
        }
    ],
    [
        {
            "id": "1ydGjYPl6SkTBwy6yhRCJT",
            "name": "Woman In Chains",
            "artists": "Tears For Fears"
        },
        {
            "id": "5jQcJ2st6yHWhUBjoDoZPH",
            "name": "Georgy Porgy",
            "artists": "TOTO"
        },
        {
            "id": "5fnOrhQ4KgT5irGCjIccGH",
            "name": "Arthur's Theme (Best That You Can Do)",
            "artists": "Christopher Cross"
        }
    ],
    [
        {
            "id": "5KgbyD2lQQlIupAaPjgiXg",
            "name": "Night Fever - From \"Saturday Night Fever\" Soundtrack",
            "artists": "Bee Gees"
        },
        {
            "id": "26QxDu518aR3rkHucaqwzM",
            "name": "THESE BOOTS ARE MADE FOR WALKIN’",
            "artists": "Nancy Sinatra"
        },
        {
            "id": "7v1858htfU0srTDwhxeka8",
            "name": "Chain Gang",
            "artists": "Sam Cooke"
        }
    ],
    [
        {
            "id": "1Xf1lWBSml62NG1du3Ro14",
            "name": "Just The Way You Are",
            "artists": "Barry White"
        },
        {
            "id": "0g8Q1Pmem92k7PzI3VLWKz",
            "name": "All at Once",
            "artists": "Whitney Houston"
        },
        {
            "id": "7pKfPomDEeI4TPT6EOYjn9",
            "name": "Imagine - Remastered 2010",
            "artists": "John Lennon"
        }
    ],
    [
        {
            "id": "5Icqjqizh8TnwHdejZQQGQ",
            "name": "Try (Just a Little Bit Harder)",
            "artists": "Janis Joplin"
        },
        {
            "id": "7cDxjUnMitNKQC5c8RQUko",
            "name": "Black Magic Woman / Gypsy Queen",
            "artists": "Santana"
        },
        {
            "id": "1tBMs9Rmw3UMvPJrsXsUyL",
            "name": "Queen of the Highway",
            "artists": "The Doors"
        }
    ],
    [
        {
            "id": "1KyCfuTbpLxr1xuXG4TuRk",
            "name": "Tell It to My Heart",
            "artists": "Taylor Dayne"
        },
        {
            "id": "4xiyq1iRdsxuU1BPUJ490Z",
            "name": "Close To Me",
            "artists": "The Cure"
        },
        {
            "id": "0X1sqQ652p1sceKM2nJlIJ",
            "name": "Runaway",
            "artists": "Bon Jovi"
        }
    ],
    [
        {
            "id": "0ZfByLXCeKchuj7zi1CJ0S",
            "name": "Stolen Dance",
            "artists": "Milky Chance"
        },
        {
            "id": "4jLv3tDBu8ww2R07DvL12s",
            "name": "Man On The Moon",
            "artists": "R.E.M."
        },
        {
            "id": "7snQQk1zcKl8gZ92AnueZW",
            "name": "Sweet Child O' Mine",
            "artists": "Guns N' Roses"
        }
    ],
    [
        {
            "id": "1EtU16em39vcCVMx2mGpHq",
            "name": "BO$$",
            "artists": "Fifth Harmony"
        },
        {
            "id": "4kte3OcW800TPvOVgrLLj8",
            "name": "Let Me Love You (Until You Learn To Love Yourself)",
            "artists": "Ne-Yo"
        },
        {
            "id": "2ndnVdR8si7CW9T8vJRHyW",
            "name": "Move Ya Body",
            "artists": "Nina Sky"
        }
    ],
    [
        {
            "id": "3stnrhzN0lzZFskbaZ5sEw",
            "name": "Scandalous - U.S. Radio Edit",
            "artists": "Mis-Teeq"
        },
        {
            "id": "6KMdMe54uoAcCdffmvyiic",
            "name": "I'm Outta Love - Hex Hector Radio Edit",
            "artists": "Anastacia"
        },
        {
            "id": "37QOvoAg1EC0PgWnfMrRmi",
            "name": "Shut Up and Let Me Go",
            "artists": "The Ting Tings"
        }
    ],
    [
        {
            "id": "4ReyTz0y3TGkX48wO3Llot",
            "name": "Epic",
            "artists": "Faith No More"
        },
        {
            "id": "1G391cbiT3v3Cywg8T7DM1",
            "name": "Scar Tissue",
            "artists": "Red Hot Chili Peppers"
        },
        {
            "id": "78lgmZwycJ3nzsdgmPPGNx",
            "name": "Immigrant Song - Remaster",
            "artists": "Led Zeppelin"
        }
    ],
    [
        {
            "id": "5WwqdeavrQrbeAMDxGawse",
            "name": "Can't Fight This Feeling",
            "artists": "REO Speedwagon"
        },
        {
            "id": "72vWcZ2qG1TcxgX5vieoVt",
            "name": "More Than You Deserve",
            "artists": "Meat Loaf"
        },
        {
            "id": "1zaiZAuhPkQfhhY9X2mTnn",
            "name": "Can the Can",
            "artists": "Suzi Quatro"
        }
    ],
    [
        {
            "id": "6JuEshIRliNXRU1LXctRjZ",
            "name": "Halah",
            "artists": "Mazzy Star"
        },
        {
            "id": "5nNZTUzinBDsnj3U76NJFC",
            "name": "And She Was - 2005 Remaster",
            "artists": "Talking Heads"
        },
        {
            "id": "7hVhRCDV100Jq26NGR7adw",
            "name": "Good Times Roll",
            "artists": "The Cars"
        }
    ],
    [
        {
            "id": "5y8d8RHvxb0KiTa9Nq0xWp",
            "name": "Morning Has Broken - Remastered 2021",
            "artists": "Yusuf / Cat Stevens"
        },
        {
            "id": "3oEkrIfXfSh9zGnE7eBzSV",
            "name": "The Winner Takes It All",
            "artists": "ABBA"
        },
        {
            "id": "0KMGxYKeUzK9wc5DZCt3HT",
            "name": "If You Leave Me Now",
            "artists": "Chicago"
        }
    ],
    [
        {
            "id": "3RkQ3UwOyPqpIiIvGVewuU",
            "name": "Mr. Tambourine Man",
            "artists": "Bob Dylan"
        },
        {
            "id": "37CRPk0L5ZpfPeePEPwE0t",
            "name": "Ashes to Ashes - 2017 Remaster",
            "artists": "David Bowie"
        },
        {
            "id": "72boGlgSwUK01n44O2tOCv",
            "name": "Lost in the Supermarket - Remastered",
            "artists": "The Clash"
        }
    ],
    [
        {
            "id": "5ir0VEsMI7cLhN6SEiaKol",
            "name": "Road",
            "artists": "Nick Drake"
        },
        {
            "id": "7mOYvqE4mvNWW0Oe3O9DxG",
            "name": "Anyone Else but You",
            "artists": "Michael Cera"
        },
        {
            "id": "3Y4rUyw7XBCK6hGHCOt6rp",
            "name": "Call It Fate, Call It Karma",
            "artists": "The Strokes"
        }
    ],
    [
        {
            "id": "23l1kVpqMVREiwU1YAlcr4",
            "name": "I Guess That's Why They Call It The Blues",
            "artists": "Elton John"
        },
        {
            "id": "3YRCqOhFifThpSRFJ1VWFM",
            "name": "November Rain",
            "artists": "Guns N' Roses"
        },
        {
            "id": "1Jaah2tmN9Hv81A87KZ1MU",
            "name": "Torn",
            "artists": "Natalie Imbruglia"
        }
    ],
    [
        {
            "id": "4OROzZUy6gOWN4UGQVaZMF",
            "name": "The Trooper - 2015 Remaster",
            "artists": "Iron Maiden"
        },
        {
            "id": "5ZBeML7Lf3FMEVviTyvi8l",
            "name": "Twist And Shout - Remastered 2009",
            "artists": "The Beatles"
        },
        {
            "id": "6xq5DxZWGgdStAxGAil0yw",
            "name": "Since You Been Gone",
            "artists": "Rainbow"
        }
    ],
    [
        {
            "id": "6Hu6dzwlvoyg3zBUC8k4BK",
            "name": "Sailing",
            "artists": "Christopher Cross"
        },
        {
            "id": "0YMFcrMtBowDdD5bPz0cgy",
            "name": "Talkin' Bout a Revolution",
            "artists": "Tracy Chapman"
        },
        {
            "id": "4I1w0J6NA3M25jFZ5dhp6y",
            "name": "Love And Affection",
            "artists": "Joan Armatrading"
        }
    ],
    [
        {
            "id": "0wEo4mwfs6tXYgCem9m9wP",
            "name": "The Wind - Remastered 2021",
            "artists": "Yusuf / Cat Stevens"
        },
        {
            "id": "3vMfr8H7hGbOLoddLdCQU4",
            "name": "Time Of The Season",
            "artists": "The Zombies"
        },
        {
            "id": "1uBmCzjv5olQzVtH1Qh1DE",
            "name": "I've Got To Have You",
            "artists": "Carly Simon"
        }
    ],
    [
        {
            "id": "3f5JtAsGRIXN8pSAeTi6vA",
            "name": "Manic Depression",
            "artists": "Jimi Hendrix"
        },
        {
            "id": "2fuCquhmrzHpu5xcA1ci9x",
            "name": "Under Pressure - Remastered 2011",
            "artists": "Queen"
        },
        {
            "id": "3RkQ3UwOyPqpIiIvGVewuU",
            "name": "Mr. Tambourine Man",
            "artists": "Bob Dylan"
        }
    ],
    [
        {
            "id": "3PbHle8KhJp6GuO1jLdEmQ",
            "name": "Be Like That",
            "artists": "3 Doors Down"
        },
        {
            "id": "2LawezPeJhN4AWuSB0GtAU",
            "name": "Have You Ever Seen The Rain",
            "artists": "Creedence Clearwater Revival"
        },
        {
            "id": "1oTo3ijRbaDAtrjJrGAPSw",
            "name": "I Miss You",
            "artists": "blink-182"
        }
    ],
    [
        {
            "id": "46eu3SBuFCXWsPT39Yg3tJ",
            "name": "Don't Stop 'Til You Get Enough",
            "artists": "Michael Jackson"
        },
        {
            "id": "44ONERBHALxftQNWq6dmyd",
            "name": "Side To Side",
            "artists": "Ariana Grande"
        },
        {
            "id": "5IKLwqBQG6KU6MP2zP80Nu",
            "name": "We Are Family - 1995 Remaster",
            "artists": "Sister Sledge"
        }
    ],
    [
        {
            "id": "1tfZtA15BfJHQTUy3dqTKC",
            "name": "Build Me Up Buttercup - Mono",
            "artists": "The Foundations"
        },
        {
            "id": "0n4bITAu0Y0nigrz3MFJMb",
            "name": "Blurred Lines",
            "artists": "Robin Thicke"
        },
        {
            "id": "2oFxITGDiTZ1JRwP8yinRt",
            "name": "On Broadway",
            "artists": "George Benson"
        }
    ],
    [
        {
            "id": "1QbOvACeYanja5pbnJbAmk",
            "name": "Take Me Home, Country Roads",
            "artists": "John Denver"
        },
        {
            "id": "5nNZTUzinBDsnj3U76NJFC",
            "name": "And She Was - 2005 Remaster",
            "artists": "Talking Heads"
        },
        {
            "id": "3TlIt0ReIxPsVZcOEivT5U",
            "name": "It's Not Unusual",
            "artists": "Tom Jones"
        }
    ],
    [
        {
            "id": "1bp2IO61zbQrbWNmKKxg3f",
            "name": "The Joker",
            "artists": "Steve Miller Band"
        },
        {
            "id": "4QlzkaRHtU8gAdwqjWmO8n",
            "name": "Friday I'm In Love",
            "artists": "The Cure"
        },
        {
            "id": "1u7kQUb3lQcpHaYRfia13A",
            "name": "And So It Goes",
            "artists": "Billy Joel"
        }
    ],
    [
        {
            "id": "70LcF31zb1H0PyJoS1Sx1r",
            "name": "Creep",
            "artists": "Radiohead"
        },
        {
            "id": "5rgDxInkX1WQJNUA7RASwi",
            "name": "Walking on both Sides",
            "artists": "Pink Turns Blue"
        },
        {
            "id": "6vTtCOimcPs5H1Jr9d0Aep",
            "name": "Sour Times",
            "artists": "Portishead"
        }
    ],
    [
        {
            "id": "7BD50ATrF3Vab5FQy7vtK8",
            "name": "How Do I Live",
            "artists": "LeAnn Rimes"
        },
        {
            "id": "0KMGxYKeUzK9wc5DZCt3HT",
            "name": "If You Leave Me Now",
            "artists": "Chicago"
        },
        {
            "id": "38zsOOcu31XbbYj9BIPUF1",
            "name": "Your Song",
            "artists": "Elton John"
        }
    ],
    [
        {
            "id": "49OMJ1prsRA7ZYgrAjz70c",
            "name": "More Than A Woman",
            "artists": "Bee Gees"
        },
        {
            "id": "7wjiMdiSgsL9Vkrwb10Num",
            "name": "On My Way - From \"Brother Bear\"/Soundtrack Version",
            "artists": "Phil Collins"
        },
        {
            "id": "3kXoKlD84c6OmIcOLfrfEs",
            "name": "September",
            "artists": "Earth, Wind & Fire"
        }
    ],
    [
        {
            "id": "4VrWlk8IQxevMvERoX08iC",
            "name": "Chandelier",
            "artists": "Sia"
        },
        {
            "id": "0puf9yIluy9W0vpMEUoAnN",
            "name": "Bang Bang",
            "artists": "Jessie J"
        },
        {
            "id": "2vPCRs3g0vdLU8sHlAEytO",
            "name": "Outrageous",
            "artists": "Britney Spears"
        }
    ],
    [
        {
            "id": "2lFFiNm0XtgJ6wkdncTB4k",
            "name": "Drive - 2017 Remaster",
            "artists": "The Cars"
        },
        {
            "id": "0Ye9OGxiHF3jylblTCuX7Q",
            "name": "Prove It All Night",
            "artists": "Bruce Springsteen"
        },
        {
            "id": "4CoSCPlKNrWli7E5kFtbcl",
            "name": "Little Lies - 2017 Remaster",
            "artists": "Fleetwood Mac"
        }
    ],
    [
        {
            "id": "4eL3n52OgIdix9aMjjTwuO",
            "name": "Any Day Above Ground",
            "artists": "James Reyne"
        },
        {
            "id": "6AttjDR4ReXvNYFm9hLOlK",
            "name": "Telephone Booth",
            "artists": "Ian Moss"
        },
        {
            "id": "2BIADdxz9kaqbMWhwpzvTX",
            "name": "I Hear Motion",
            "artists": "Models"
        }
    ],
    [
        {
            "id": "0nnwn7LWHCAu09jfuH1xTA",
            "name": "Slide",
            "artists": "The Goo Goo Dolls"
        },
        {
            "id": "7bu0znpSbTks0O6I98ij0W",
            "name": "Tonight, Tonight - Remastered 2012",
            "artists": "The Smashing Pumpkins"
        },
        {
            "id": "1yKu2MhpwzDXXH2tzG6xoa",
            "name": "Beverly Hills",
            "artists": "Weezer"
        }
    ],
    [
        {
            "id": "2uIX8YMNjGMD7441kqyyNU",
            "name": "ocean eyes",
            "artists": "Billie Eilish"
        },
        {
            "id": "7BKLCZ1jbUBVqRi2FVlTVw",
            "name": "Closer",
            "artists": "The Chainsmokers"
        },
        {
            "id": "15JINEqzVMv3SvJTAXAKED",
            "name": "Love The Way You Lie",
            "artists": "Eminem"
        }
    ],
    [
        {
            "id": "6I4snLrVOrJsLdd43isc27",
            "name": "A View to a Kill",
            "artists": "Duran Duran"
        },
        {
            "id": "5jzma6gCzYtKB1DbEwFZKH",
            "name": "London Calling - Remastered",
            "artists": "The Clash"
        },
        {
            "id": "0dOg1ySSI7NkpAe89Zo0b9",
            "name": "Born in the U.S.A.",
            "artists": "Bruce Springsteen"
        }
    ],
    [
        {
            "id": "1MXOWbSCEjoGwivtIMnlBV",
            "name": "Constellations",
            "artists": "Duster"
        },
        {
            "id": "4mWahKerLaVddUjb8d1Q4Q",
            "name": "The Man Who Sold the World - 2015 Remaster",
            "artists": "David Bowie"
        },
        {
            "id": "5QLHGv0DfpeXLNFo7SFEy1",
            "name": "1979 - Remastered 2012",
            "artists": "The Smashing Pumpkins"
        }
    ],
    [
        {
            "id": "63OQupATfueTdZMWTxW03A",
            "name": "Karma Police",
            "artists": "Radiohead"
        },
        {
            "id": "3MrWxJaD2AT0W9DjWF64Vm",
            "name": "Come On Eileen",
            "artists": "Dexys Midnight Runners"
        },
        {
            "id": "5fbQCQt91LsVgXusFS0CCD",
            "name": "Disorder - 2007 Remaster",
            "artists": "Joy Division"
        }
    ],
    [
        {
            "id": "74BiRtgDe2YPETdTCcsXoG",
            "name": "All Cried Out",
            "artists": "Alison Moyet"
        },
        {
            "id": "5fqC8Ms9SOr6Bz4KJ5P4eC",
            "name": "Said It All",
            "artists": "Take That"
        },
        {
            "id": "7jley98gCQFueQ5MCaFWIb",
            "name": "All Rise",
            "artists": "Blue"
        }
    ],
    [
        {
            "id": "5Hroj5K7vLpIG4FNCRIjbP",
            "name": "Best Day Of My Life",
            "artists": "American Authors"
        },
        {
            "id": "2N0volXQpwsvjDorTTxBAU",
            "name": "Bonfire Heart",
            "artists": "James Blunt"
        },
        {
            "id": "1gihuPhrLraKYrJMAEONyc",
            "name": "Feel So Close - Radio Edit",
            "artists": "Calvin Harris"
        }
    ],
    [
        {
            "id": "4jDmJ51x1o9NZB5Nxxc7gY",
            "name": "Careless Whisper",
            "artists": "George Michael"
        },
        {
            "id": "2AkmdLbVKS1steeZdy8H1l",
            "name": "I Want To Break Free - Single Remix",
            "artists": "Queen"
        },
        {
            "id": "1wrT33b6HuKlpk9ziscEUY",
            "name": "Baby Jane - 2008 Remaster",
            "artists": "Rod Stewart"
        }
    ],
    [
        {
            "id": "1Z7C8ClE8UEaH70jCCeJH2",
            "name": "Ten Crack Commandments - 2014 Remaster",
            "artists": "The Notorious B.I.G."
        },
        {
            "id": "5IFCyWplye09HytIP80RCF",
            "name": "Too Close",
            "artists": "Next"
        },
        {
            "id": "4fxF8ljwryMZX5c9EKrLFE",
            "name": "Boombastic",
            "artists": "Shaggy"
        }
    ],
    [
        {
            "id": "0yJvWbn8xQKiDZ84VN5lQG",
            "name": "De Do Do Do, De Da Da Da",
            "artists": "The Police"
        },
        {
            "id": "5hhVpGIBlqAU5yJEOmrk5o",
            "name": "All My Love - Remaster",
            "artists": "Led Zeppelin"
        },
        {
            "id": "2ciMJGCDW70hqq18Vgui68",
            "name": "Who'll Stop The Rain",
            "artists": "Creedence Clearwater Revival"
        }
    ],
    [
        {
            "id": "7FwBtcecmlpc1sLySPXeGE",
            "name": "Dancing In the Dark",
            "artists": "Bruce Springsteen"
        },
        {
            "id": "1D2QnxvMOac95EG9C0KbsJ",
            "name": "So In Love",
            "artists": "Orchestral Manoeuvres In The Dark"
        },
        {
            "id": "1Pd1h30mgU05QkWYhgFzwt",
            "name": "Turn to Stone",
            "artists": "Electric Light Orchestra"
        }
    ],
    [
        {
            "id": "6AioOohg4bQZFA4jIYQQ2r",
            "name": "Forty Six & 2",
            "artists": "TOOL"
        },
        {
            "id": "5BnFZLH99sYav2cxJFGO2n",
            "name": "Gone Away - 1997",
            "artists": "The Offspring"
        },
        {
            "id": "3AwLxSqo1jOOMpNsgxqRNE",
            "name": "Prison Song",
            "artists": "System Of A Down"
        }
    ],
    [
        {
            "id": "648BMGrt98kUbLo24A4vgj",
            "name": "Hip To Be Square",
            "artists": "Huey Lewis & The News"
        },
        {
            "id": "3kypZy0F0R2oTOkAZJG7Tb",
            "name": "Sweet Dreams (Are Made of This)",
            "artists": "Eurythmics"
        },
        {
            "id": "0L0T4tMAaGqLgIVj1MOj9t",
            "name": "Father Figure - Remastered",
            "artists": "George Michael"
        }
    ],
    [
        {
            "id": "1lCC3flXDsXQrNPcvDojuI",
            "name": "Vietnow",
            "artists": "Rage Against The Machine"
        },
        {
            "id": "2UoHjfejHhemj0KSWCOV2A",
            "name": "Jesus Christ Pose - Remastered 2016",
            "artists": "Soundgarden"
        },
        {
            "id": "2gz6rDUWhKn1XWi7iapbpm",
            "name": "4am",
            "artists": "Our Lady Peace"
        }
    ],
    [
        {
            "id": "1Eb90nmqTrxylKFhcUzW8P",
            "name": "(Everything I Do) I Do It For You",
            "artists": "Bryan Adams"
        },
        {
            "id": "7w57O4o0xCTn9YpKuaPZDd",
            "name": "The Great Beyond",
            "artists": "R.E.M."
        },
        {
            "id": "5EQzuYfTZt7B2LqlvTF49l",
            "name": "It's All Coming Back to Me Now",
            "artists": "Céline Dion"
        }
    ],
    [
        {
            "id": "0L0T4tMAaGqLgIVj1MOj9t",
            "name": "Father Figure - Remastered",
            "artists": "George Michael"
        },
        {
            "id": "1Jo0Zg7XlrA6z0mFTZVdkn",
            "name": "Don't Stop The Music",
            "artists": "Rihanna"
        },
        {
            "id": "4rDbp1vnvEhieiccprPMdI",
            "name": "Somebody To Love - Remastered 2011",
            "artists": "Queen"
        }
    ],
    [
        {
            "id": "77MdvMx9L4ZQuLhhn3o21h",
            "name": "If the World Was Ending (feat. Julia Michaels)",
            "artists": "JP Saxe"
        },
        {
            "id": "2P4OICZRVAQcYAV2JReRfj",
            "name": "Waiting For Love",
            "artists": "Avicii"
        },
        {
            "id": "6lanRgr6wXibZr8KgzXxBl",
            "name": "a thousand years",
            "artists": "Christina Perri"
        }
    ],
    [
        {
            "id": "5JJDu0Z5DKe7mR31MGksSg",
            "name": "Come Out and Play",
            "artists": "The Offspring"
        },
        {
            "id": "1ndGB6rvxKYN9seCYO1dTF",
            "name": "The Zephyr Song",
            "artists": "Red Hot Chili Peppers"
        },
        {
            "id": "5FZxsHWIvUsmSK1IAvm2pp",
            "name": "Best of You",
            "artists": "Foo Fighters"
        }
    ],
    [
        {
            "id": "77NwdlKUIMS3gvvJeO5KK1",
            "name": "Something About You",
            "artists": "Level 42"
        },
        {
            "id": "5RYLa5P4qweEAKq5U1gdcK",
            "name": "A Kind Of Magic - Remastered 2011",
            "artists": "Queen"
        },
        {
            "id": "4wLjiz87aGbmDhADeMQWwt",
            "name": "Hand to Mouth - Remastered",
            "artists": "George Michael"
        }
    ],
    [
        {
            "id": "3G69vJMWsX6ZohTykad2AU",
            "name": "One",
            "artists": "U2"
        },
        {
            "id": "46eu3SBuFCXWsPT39Yg3tJ",
            "name": "Don't Stop 'Til You Get Enough",
            "artists": "Michael Jackson"
        },
        {
            "id": "0G21yYKMZoHa30cYVi1iA8",
            "name": "Welcome To The Jungle",
            "artists": "Guns N' Roses"
        }
    ],
    [
        {
            "id": "79MMMdYL00iwKVHBSAUkLY",
            "name": "I Wanna Be Your Dog - 2019 Remaster",
            "artists": "The Stooges"
        },
        {
            "id": "4gMgiXfqyzZLMhsksGmbQV",
            "name": "Another Brick in the Wall, Pt. 2",
            "artists": "Pink Floyd"
        },
        {
            "id": "2LXISHBkx8FyoxCBkckh19",
            "name": "Do It Again",
            "artists": "Steely Dan"
        }
    ],
    [
        {
            "id": "6z2AyfE9GZxoHqJVSA4NgN",
            "name": "Susie Q",
            "artists": "Creedence Clearwater Revival"
        },
        {
            "id": "5Sz09kaSzvpTC8lgm5W8Mt",
            "name": "Mustang Sally",
            "artists": "Wilson Pickett"
        },
        {
            "id": "4pGWgMDgwUQiKOHBUJquKd",
            "name": "Real Real Gone",
            "artists": "Van Morrison"
        }
    ],
    [
        {
            "id": "1iSoJ2JLCSsWxeszKqQuBJ",
            "name": "Last Night of My Life",
            "artists": "Choirboys"
        },
        {
            "id": "2lksJ7oUYRD3BgH0uix9gy",
            "name": "Love Your Way",
            "artists": "Powderfinger"
        },
        {
            "id": "1tFgbvRzyEaIhnVRqCwJy9",
            "name": "Out Of Mind Out Of Sight",
            "artists": "Models"
        }
    ],
    [
        {
            "id": "7fnkRaUfAxrQJAT9df8h3t",
            "name": "Shut Down - Remastered",
            "artists": "Australian Crawl"
        },
        {
            "id": "6rvldt6EoZwzogApECUCwd",
            "name": "Who Made Who",
            "artists": "AC/DC"
        },
        {
            "id": "0jdwA2pPXiVltojQt72yZD",
            "name": "The Dead Heart",
            "artists": "Midnight Oil"
        }
    ],
    [
        {
            "id": "2lksJ7oUYRD3BgH0uix9gy",
            "name": "Love Your Way",
            "artists": "Powderfinger"
        },
        {
            "id": "6wLOCD9Wj8dl0xNf9sDHw5",
            "name": "Compulsory Hero - Live",
            "artists": "1927"
        },
        {
            "id": "0DCt37rdJ8laTNsti0d1j7",
            "name": "Women In Uniform",
            "artists": "Skyhooks"
        }
    ],
    [
        {
            "id": "5cc9Zbfp9u10sfJeKZ3h16",
            "name": "3005",
            "artists": "Childish Gambino"
        },
        {
            "id": "6C3yPXYG2NJYlIYVe5J7hv",
            "name": "I'll Be There For You/You're All I Need To Get By - Puff Daddy Mix",
            "artists": "Method Man"
        },
        {
            "id": "0snDRsjNRMJhm7SVja8l6J",
            "name": "MC's Act Like They Don't Know",
            "artists": "KRS-One"
        }
    ],
    [
        {
            "id": "3haZcHm3HydDVxm3je3Zmg",
            "name": "Help Me, Rhonda - Single Version/Remastered 2001",
            "artists": "The Beach Boys"
        },
        {
            "id": "4QMvxtZGcmvwWtmmoiRs5B",
            "name": "Will You Love Me Tomorrow",
            "artists": "The Shirelles"
        },
        {
            "id": "73m8WuJlhzVusTVzJCGaDZ",
            "name": "Fever",
            "artists": "Elvis Presley"
        }
    ],
    [
        {
            "id": "0x4QNK9QwkGgTEgNcxQaX9",
            "name": "Naked in Front of the Computer - 2016 Remaster",
            "artists": "Faith No More"
        },
        {
            "id": "0wzRcekWyVCSyPtlPOeJau",
            "name": "Go With The Flow",
            "artists": "Queens of the Stone Age"
        },
        {
            "id": "0M5xRyxGpFFDfzN2x0wdpH",
            "name": "Hey, Johnny Park!",
            "artists": "Foo Fighters"
        }
    ],
    [
        {
            "id": "5MzjQ95rdB2xt9DNa2IzaC",
            "name": "Don't Phunk With My Heart",
            "artists": "Black Eyed Peas"
        },
        {
            "id": "3uwnnTQcHM1rDqSfA4gQNz",
            "name": "Cool for the Summer",
            "artists": "Demi Lovato"
        },
        {
            "id": "1bhUWB0zJMIKr9yVPrkEuI",
            "name": "Perfect Duet (Ed Sheeran & Beyoncé)",
            "artists": "Ed Sheeran"
        }
    ],
    [
        {
            "id": "5axOkQnmQmwtjr4bv1Xt7i",
            "name": "I Don't Wanna Stop",
            "artists": "Ozzy Osbourne"
        },
        {
            "id": "43GS3mtezoIFiuIZCLLiDY",
            "name": "Every Rose Has Its Thorn - 2003 Remaster",
            "artists": "Poison"
        },
        {
            "id": "0v1XpBHnsbkCn7iJ9Ucr1l",
            "name": "It's My Life",
            "artists": "Bon Jovi"
        }
    ],
    [
        {
            "id": "270N4xGB60dza0AoB1tT9a",
            "name": "Caribbean Queen (No More Love On the Run)",
            "artists": "Billy Ocean"
        },
        {
            "id": "2eHj0klWkwRQuIrNlPpCPa",
            "name": "I'm Every Woman",
            "artists": "Whitney Houston"
        },
        {
            "id": "5NRLokkZKwYxIn6zMFU3yM",
            "name": "Girl You Know It's True - N.Y.C.Subway Remix",
            "artists": "Milli Vanilli"
        }
    ],
    [
        {
            "id": "4LI7LqBRuXxLyEZ2fCQnit",
            "name": "Out of Touch",
            "artists": "Daryl Hall & John Oates"
        },
        {
            "id": "7G7tgVYORlDuVprcYHuFJh",
            "name": "Don't Dream It's Over",
            "artists": "Crowded House"
        },
        {
            "id": "3qiyyUfYe7CRYLucrPmulD",
            "name": "Baba O'Riley",
            "artists": "The Who"
        }
    ],
    [
        {
            "id": "4uvjOKsp7mSjrDhWdkLPBY",
            "name": "I Think We're Alone Now",
            "artists": "Tiffany"
        },
        {
            "id": "7G7tgVYORlDuVprcYHuFJh",
            "name": "Don't Dream It's Over",
            "artists": "Crowded House"
        },
        {
            "id": "7aQjPecQdIuNd1sz3KCDhD",
            "name": "Lovefool",
            "artists": "The Cardigans"
        }
    ],
    [
        {
            "id": "2K2M0TcglCRLLpFOzKeFZA",
            "name": "Sunshine Of Your Love",
            "artists": "Cream"
        },
        {
            "id": "05ajrG3EAcIe3j7NuqRV9B",
            "name": "Alright (2015 Remaster)",
            "artists": "Supergrass"
        },
        {
            "id": "3dmqIB2Qxe2XZobw9gXxJ6",
            "name": "Mary Jane's Last Dance",
            "artists": "Tom Petty and the Heartbreakers"
        }
    ],
    [
        {
            "id": "6urCAbunOQI4bLhmGpX7iS",
            "name": "Don't Speak",
            "artists": "No Doubt"
        },
        {
            "id": "71MfSDt9aSa43hcFQNYW8w",
            "name": "Perfect - 2015 Remaster",
            "artists": "Alanis Morissette"
        },
        {
            "id": "6mYrhCAGWzTdF8QnKuchXM",
            "name": "If I Could Turn Back Time",
            "artists": "Cher"
        }
    ],
    [
        {
            "id": "3MFFDRC4wTN9JNGtzXsZlN",
            "name": "Love Her Madly",
            "artists": "The Doors"
        },
        {
            "id": "5EWPGh7jbTNO2wakv8LjUI",
            "name": "Free Bird",
            "artists": "Lynyrd Skynyrd"
        },
        {
            "id": "7LbfuQVct78YoghmoPtsQ8",
            "name": "Casey Jones - 2013 Remaster",
            "artists": "Grateful Dead"
        }
    ],
    [
        {
            "id": "37BTh5g05cxBIRYMbw8g2T",
            "name": "Rosanna",
            "artists": "TOTO"
        },
        {
            "id": "62AuGbAkt8Ox2IrFFb8GKV",
            "name": "Sweet Caroline",
            "artists": "Neil Diamond"
        },
        {
            "id": "67eX1ovaHyVPUinMHeUtIM",
            "name": "Hurts So Good",
            "artists": "John Mellencamp"
        }
    ],
    [
        {
            "id": "71bjBioywI00PasN2yHKfZ",
            "name": "Hit and Run",
            "artists": "Jo Jo Zep and The Falcons"
        },
        {
            "id": "6YYvKTOuk0ThSzukDchTfd",
            "name": "Evie (Evie)",
            "artists": "Stevie Wright"
        },
        {
            "id": "0NKv1n25UpKKhZbp5UVV6P",
            "name": "April Sun in Cuba",
            "artists": "Dragon"
        }
    ],
    [
        {
            "id": "7LwsqxyIqOCF9vbdHmdIvT",
            "name": "Dangerous",
            "artists": "Roxette"
        },
        {
            "id": "2YhE6xeWN0R9RVwEOG9lR1",
            "name": "Candy",
            "artists": "Mandy Moore"
        },
        {
            "id": "3ZFTkvIE7kyPt6Nu3PEa7V",
            "name": "Hips Don't Lie (feat. Wyclef Jean)",
            "artists": "Shakira"
        }
    ],
    [
        {
            "id": "1b6fmULpHj08RMmHfARJ4e",
            "name": "Selfish",
            "artists": "Little Simz"
        },
        {
            "id": "7w5OIjIAaXlLmOSbBhD0bw",
            "name": "Relaxed Lizard",
            "artists": "Soft Hair"
        },
        {
            "id": "0lOzGDHcPlUB1ZvXMWQ0Oh",
            "name": "One Too Many Mornings",
            "artists": "The Chemical Brothers"
        }
    ],
    [
        {
            "id": "6Hu6dzwlvoyg3zBUC8k4BK",
            "name": "Sailing",
            "artists": "Christopher Cross"
        },
        {
            "id": "2LVxvGhl2U5p2ql2ujc6vZ",
            "name": "Hands Clean",
            "artists": "Alanis Morissette"
        },
        {
            "id": "04OjLvOApQve45B0ISx4XN",
            "name": "I Want to Know What Love Is",
            "artists": "Foreigner"
        }
    ],
    [
        {
            "id": "5GGTgkmfEzkhAfmG0hxXk9",
            "name": "Champagne Supernova",
            "artists": "Oasis"
        },
        {
            "id": "0wzRcekWyVCSyPtlPOeJau",
            "name": "Go With The Flow",
            "artists": "Queens of the Stone Age"
        },
        {
            "id": "6kopmMZiyLmw7h66uXcXR7",
            "name": "Valerie (feat. Amy Winehouse) - Version Revisited",
            "artists": "Mark Ronson"
        }
    ],
    [
        {
            "id": "7j5TIXPi0cCbSSqItmbyZy",
            "name": "Vogue",
            "artists": "Madonna"
        },
        {
            "id": "6UXXeFqMBGiqjkzQzkMT3E",
            "name": "Tragedy",
            "artists": "Bee Gees"
        },
        {
            "id": "1AWQoqb9bSvzTjaLralEkT",
            "name": "Rock Your Body",
            "artists": "Justin Timberlake"
        }
    ],
    [
        {
            "id": "3Dfy8YIxq89i84t108TvMi",
            "name": "Love Bites - Remastered 2017",
            "artists": "Def Leppard"
        },
        {
            "id": "4kfm1uI9QGaoN9qm6CkAMn",
            "name": "What I've Done",
            "artists": "Linkin Park"
        },
        {
            "id": "5EWtBjCLy21d1hY9zdaEe8",
            "name": "Keep The Faith",
            "artists": "Bon Jovi"
        }
    ],
    [
        {
            "id": "41TVMXb9THdtTlo2KojUDe",
            "name": "Somebody to Shove (2022 Remaster)",
            "artists": "Soul Asylum"
        },
        {
            "id": "3u9mrgTJ7SwcBq5Vxye64G",
            "name": "Song Without Sin",
            "artists": "Living Colour"
        },
        {
            "id": "4sIgX7HWCtfxIGXv4QM1RL",
            "name": "American Horse",
            "artists": "The Cult"
        }
    ],
    [
        {
            "id": "4eHbdreAnSOrDDsFfc4Fpm",
            "name": "I Will Always Love You",
            "artists": "Whitney Houston"
        },
        {
            "id": "2374M0fQpWi3dLnB54qaLX",
            "name": "Africa",
            "artists": "TOTO"
        },
        {
            "id": "0DuWDLjriRPjDRoPgaCslY",
            "name": "Love In The Dark",
            "artists": "Adele"
        }
    ],
    [
        {
            "id": "7o7E1nrHWncYY7PY94gCiX",
            "name": "Video Killed The Radio Star",
            "artists": "The Buggles"
        },
        {
            "id": "38zsOOcu31XbbYj9BIPUF1",
            "name": "Your Song",
            "artists": "Elton John"
        },
        {
            "id": "3FAclTFfvUuQYnEsptbK8w",
            "name": "Back To Black",
            "artists": "Amy Winehouse"
        }
    ],
    [
        {
            "id": "04lTbtPmiRzwsxZRs2sdk9",
            "name": "Volunteers - Remastered",
            "artists": "Jefferson Airplane"
        },
        {
            "id": "1oV1tu8utgHQjLJsEK9sVl",
            "name": "Take Me to the River - 2005 Remaster",
            "artists": "Talking Heads"
        },
        {
            "id": "48i055G1OT5KxGGftwFxWy",
            "name": "Oh, Pretty Woman",
            "artists": "Roy Orbison"
        }
    ],
    [
        {
            "id": "7f1Dmr246cJ9uQYdbplTbh",
            "name": "He Wasn't Man Enough",
            "artists": "Toni Braxton"
        },
        {
            "id": "2H4MC4UVMBqDmv7pd8jX1v",
            "name": "Goodies (feat. Petey Pablo)",
            "artists": "Ciara"
        },
        {
            "id": "4DiNls6kFmF1ZittKsPsTc",
            "name": "Mr. Telephone Man",
            "artists": "New Edition"
        }
    ],
    [
        {
            "id": "4ls9aNVGSLhaIzfiVTqTyj",
            "name": "Who Knows Where The Time Goes?",
            "artists": "Fairport Convention"
        },
        {
            "id": "1yupbrI7ROhigIHpQBevPh",
            "name": "Chicago",
            "artists": "Sufjan Stevens"
        },
        {
            "id": "0620OecAlwJQxWieRW4L9s",
            "name": "Bless the Telephone",
            "artists": "Labi Siffre"
        }
    ],
    [
        {
            "id": "3QZ7uX97s82HFYSmQUAN1D",
            "name": "Tom Sawyer",
            "artists": "Rush"
        },
        {
            "id": "4bO6DljpuAeQh6HS20i0I5",
            "name": "Money For Nothing",
            "artists": "Dire Straits"
        },
        {
            "id": "0qi4b1l0eT3jpzeNHeFXDT",
            "name": "Just Can't Get Enough",
            "artists": "Depeche Mode"
        }
    ],
    [
        {
            "id": "1kIu9zpYtWjgrLlsactlna",
            "name": "Jump (Original Mix)",
            "artists": "The Pointer Sisters"
        },
        {
            "id": "6Nd6ntkzr4t8o1FKPGOSMt",
            "name": "Here I Go Again - 2018 Remaster",
            "artists": "Whitesnake"
        },
        {
            "id": "17S4XrLvF5jlGvGCJHgF51",
            "name": "Learning To Fly",
            "artists": "Tom Petty and the Heartbreakers"
        }
    ],
    [
        {
            "id": "787o3k4IEWqFUA9mNus4dM",
            "name": "The Three Keys",
            "artists": "Marcus Bentham"
        },
        {
            "id": "521lcnJ07UXF5HV1gotHdU",
            "name": "Something on Your Mind",
            "artists": "Karen Dalton"
        },
        {
            "id": "6ziQDVHvXcKm7N78CBNjY6",
            "name": "Black Soul Choir",
            "artists": "16 Horsepower"
        }
    ],
    [
        {
            "id": "3TlIt0ReIxPsVZcOEivT5U",
            "name": "It's Not Unusual",
            "artists": "Tom Jones"
        },
        {
            "id": "3nFJbZCHP4d9vduKjJLdBL",
            "name": "Never Too Much",
            "artists": "Luther Vandross"
        },
        {
            "id": "5hXEcqQhEjfZdbIZLO8mf2",
            "name": "Everything She Wants",
            "artists": "Wham!"
        }
    ],
    [
        {
            "id": "487uZHjPqwQWAMKdabHJnZ",
            "name": "Filthy/Gorgeous",
            "artists": "Scissor Sisters"
        },
        {
            "id": "1PEqh7awkpuepLBSq8ZwqD",
            "name": "I Love You Always Forever",
            "artists": "Donna Lewis"
        },
        {
            "id": "4TOGkYS141L15SkVosAp7Z",
            "name": "It's My Life",
            "artists": "Dr. Alban"
        }
    ],
    [
        {
            "id": "7n3WO6ESKS1uCI9fgkGs66",
            "name": "I'd Love to Change the World - 2004 Remaster",
            "artists": "Ten Years After"
        },
        {
            "id": "3CmHvyZQQAGkKkTjTBFWN6",
            "name": "Have a Cigar",
            "artists": "Pink Floyd"
        },
        {
            "id": "3ix6K4wZY29bCujrSznwFZ",
            "name": "Let's Dance - 2018 Remaster",
            "artists": "David Bowie"
        }
    ],
    [
        {
            "id": "62LJFaYihsdVrrkgUOJC05",
            "name": "Kiss",
            "artists": "Prince"
        },
        {
            "id": "1MsBRSbt5dqJSw3RxXtvCM",
            "name": "I Want To Break Free - Remastered 2011",
            "artists": "Queen"
        },
        {
            "id": "1mMYaXpT65iZDtvfRA9EkE",
            "name": "Fresh",
            "artists": "Kool & The Gang"
        }
    ],
    [
        {
            "id": "7k1fu2zeQ3S47mT4lhJWcL",
            "name": "Modern Girl",
            "artists": "Sheena Easton"
        },
        {
            "id": "0E1PR66A94yVPiYJxGHimf",
            "name": "Instant Replay",
            "artists": "Dan Hartman"
        },
        {
            "id": "0EYigGnn91koV8IhpDjCrG",
            "name": "Jump (For My Love) - Single Remix",
            "artists": "The Pointer Sisters"
        }
    ],
    [
        {
            "id": "4z7maGZkAonDlXlwo8q69f",
            "name": "Da Ya Think I'm Sexy?",
            "artists": "Rod Stewart"
        },
        {
            "id": "46kumCAwe7ylgfMzkM62LY",
            "name": "In the stone - EARTH, WIND & FIRE LIVE IN VELFARRE_1995.4.20",
            "artists": "Earth, Wind & Fire"
        },
        {
            "id": "2Nz6aF1umHh5Et6I5H581L",
            "name": "Hooked On A Feeling",
            "artists": "Blue Swede"
        }
    ],
    [
        {
            "id": "3BZGi1yUqQyCNC868AqUGG",
            "name": "Big in Japan",
            "artists": "Alphaville"
        },
        {
            "id": "5lwQGZYF4BXOzFtXc5zk8q",
            "name": "Head Over Heels - Dave Bascombe 7\" N.Mix",
            "artists": "Tears For Fears"
        },
        {
            "id": "43h4FonpCeaaURpFpiQsf9",
            "name": "Hold Me Now",
            "artists": "Thompson Twins"
        }
    ],
    [
        {
            "id": "5yMXAaSvxo12QkYU75Ixv0",
            "name": "Luka",
            "artists": "Suzanne Vega"
        },
        {
            "id": "0qxYx4F3vm1AOnfux6dDxP",
            "name": "You Can Call Me Al",
            "artists": "Paul Simon"
        },
        {
            "id": "2Ms33RTRCT6gArrpcrPxmo",
            "name": "Feel",
            "artists": "Robbie Williams"
        }
    ],
    [
        {
            "id": "6Wn3pdFtAcnYJyJVITwt7N",
            "name": "Girls Got Rhythm",
            "artists": "AC/DC"
        },
        {
            "id": "6xMHglHoafdDFGXS6qfwSH",
            "name": "Hot Blooded",
            "artists": "Foreigner"
        },
        {
            "id": "11DjZQEZ69EXLo77HVj6yW",
            "name": "Green River",
            "artists": "Creedence Clearwater Revival"
        }
    ],
    [
        {
            "id": "0p8J2iQUu26CMVPgwYyYuV",
            "name": "Hit & Run",
            "artists": "Jo Jo Zep and The Falcons"
        },
        {
            "id": "78mKzDM4AF4hGXUryZaa9E",
            "name": "Let the Franklin Flow - Live; Remastered Version",
            "artists": "Goanna"
        },
        {
            "id": "4UcyOfLghWkhXwWfOMnCl9",
            "name": "Chemistry - Digitally Remastered",
            "artists": "Mondo Rock"
        }
    ],
    [
        {
            "id": "7G67ZJRQT9nn2Fa9vA6B32",
            "name": "Original Sin",
            "artists": "INXS"
        },
        {
            "id": "1BvJmtaXsqtH438BcDPeBb",
            "name": "Daniel",
            "artists": "Elton John"
        },
        {
            "id": "1pTGc8pwyo6xtgXBKCBcFn",
            "name": "Woman in Love",
            "artists": "Barbra Streisand"
        }
    ],
    [
        {
            "id": "4yQw7FR9lcvL6RHtegbJBh",
            "name": "Think",
            "artists": "Aretha Franklin"
        },
        {
            "id": "5p3JunprHCxClJjOmcLV8G",
            "name": "Walk On the Wild Side",
            "artists": "Lou Reed"
        },
        {
            "id": "4SGBuq37Ol4HJr7pQqFMKa",
            "name": "I Got You Babe",
            "artists": "Sonny & Cher"
        }
    ],
    [
        {
            "id": "1hHGUdFaiJHw9hVZGJWYO2",
            "name": "Midnight Rider",
            "artists": "Allman Brothers Band"
        },
        {
            "id": "2nvcTDmZkRWKNMAL29sLHo",
            "name": "The Night They Drove Old Dixie Down",
            "artists": "The Band"
        },
        {
            "id": "4OMu5a8sFpcRCPCcsoEaov",
            "name": "Babe I'm Gonna Leave You - 1990 Remaster",
            "artists": "Led Zeppelin"
        }
    ],
    [
        {
            "id": "08mG3Y1vljYA6bvDt4Wqkj",
            "name": "Back In Black",
            "artists": "AC/DC"
        },
        {
            "id": "6Rf4L61dBRNsuE6BYkJYFL",
            "name": "Holiday",
            "artists": "Green Day"
        },
        {
            "id": "2K2M0TcglCRLLpFOzKeFZA",
            "name": "Sunshine Of Your Love",
            "artists": "Cream"
        }
    ],
    [
        {
            "id": "4xiyq1iRdsxuU1BPUJ490Z",
            "name": "Close To Me",
            "artists": "The Cure"
        },
        {
            "id": "4WoKuMjwJXuy9IqX6AH5JE",
            "name": "People Are People",
            "artists": "Depeche Mode"
        },
        {
            "id": "3iA4foXIFpekwHyma7pRs1",
            "name": "Overkill",
            "artists": "Men At Work"
        }
    ],
    [
        {
            "id": "37pK088xTo1ZpR3y23wsFk",
            "name": "Arms Of A Woman",
            "artists": "Amos Lee"
        },
        {
            "id": "5G4W4UzaJIpYl0ar95Cs17",
            "name": "Tupelo Honey",
            "artists": "Van Morrison"
        },
        {
            "id": "3dmqIB2Qxe2XZobw9gXxJ6",
            "name": "Mary Jane's Last Dance",
            "artists": "Tom Petty and the Heartbreakers"
        }
    ],
    [
        {
            "id": "418gyIJdAZSZisVdzDXLNc",
            "name": "Wild Horses",
            "artists": "The Sundays"
        },
        {
            "id": "5mFyCVEII6mp5YPPYQfTck",
            "name": "Innocent",
            "artists": "Our Lady Peace"
        },
        {
            "id": "6dDxgfvM8pJm7AzmLZB1nN",
            "name": "Such Great Heights",
            "artists": "Iron & Wine"
        }
    ],
    [
        {
            "id": "29SRvYOKbMLOZeOubNGtLb",
            "name": "Is She Really Going Out With Him?",
            "artists": "Joe Jackson"
        },
        {
            "id": "0WCXFE3RTTUzhufeeee227",
            "name": "Every Little Kiss",
            "artists": "Bruce Hornsby and the Range"
        },
        {
            "id": "1dMilrhgON9TIGPVdWG2dX",
            "name": "Throwing It All Away - 2007 Remaster",
            "artists": "Genesis"
        }
    ],
    [
        {
            "id": "5mJGLBNJM0GULqAoL5mb9C",
            "name": "Breed",
            "artists": "Nirvana"
        },
        {
            "id": "48UPSzbZjgc449aqz8bxox",
            "name": "Californication",
            "artists": "Red Hot Chili Peppers"
        },
        {
            "id": "1llY5gzWqdAjm1Hscr4kwn",
            "name": "Mis",
            "artists": "Alex G"
        }
    ],
    [
        {
            "id": "4hObp5bmIJ3PP3cKA9K9GY",
            "name": "Don't Worry Be Happy",
            "artists": "Bobby McFerrin"
        },
        {
            "id": "0SiywuOBRcynK0uKGWdCnn",
            "name": "Bad Romance",
            "artists": "Lady Gaga"
        },
        {
            "id": "2HhBmnL8kVYaevaaCsnMVB",
            "name": "Heart Of Glass - Remix",
            "artists": "Blondie"
        }
    ],
    [
        {
            "id": "3ix6K4wZY29bCujrSznwFZ",
            "name": "Let's Dance - 2018 Remaster",
            "artists": "David Bowie"
        },
        {
            "id": "4wH4dJgrsxONID6KS2tDQM",
            "name": "Maneater",
            "artists": "Nelly Furtado"
        },
        {
            "id": "5BCykgPXc7zEBg2oU0klvy",
            "name": "Who Can It Be Now?",
            "artists": "Men At Work"
        }
    ],
    [
        {
            "id": "5ZBeML7Lf3FMEVviTyvi8l",
            "name": "Twist And Shout - Remastered 2009",
            "artists": "The Beatles"
        },
        {
            "id": "0LxeKwg9t7HOnyfv4bTALT",
            "name": "Suck It and See",
            "artists": "Arctic Monkeys"
        },
        {
            "id": "6ITuEsxEy2qPhqMowdDAeI",
            "name": "Train in Vain (Stand by Me) - Remastered",
            "artists": "The Clash"
        }
    ],
    [
        {
            "id": "1BV0m40U0M4t1SLIsDnwZl",
            "name": "1973",
            "artists": "James Blunt"
        },
        {
            "id": "6RUKPb4LETWmmr3iAEQktW",
            "name": "Something Just Like This",
            "artists": "The Chainsmokers"
        },
        {
            "id": "0lYBSQXN6rCTvUZvg9S0lU",
            "name": "Let Me Love You",
            "artists": "DJ Snake"
        }
    ],
    [
        {
            "id": "7kzKAuUzOITUauHAhoMoxA",
            "name": "Last Nite",
            "artists": "The Strokes"
        },
        {
            "id": "1L2ZkXbRX00ZiaUDuMMgf7",
            "name": "Floods",
            "artists": "Pantera"
        },
        {
            "id": "679zqcQuKakOGI93NPCqB8",
            "name": "Present Tense",
            "artists": "Pearl Jam"
        }
    ],
    [
        {
            "id": "38TuEl4QqLM1VtJ5LK6FK0",
            "name": "Automatic",
            "artists": "The Pointer Sisters"
        },
        {
            "id": "1rnj7wb0tQc2Pmg6pfIffF",
            "name": "Locomotion",
            "artists": "Orchestral Manoeuvres In The Dark"
        },
        {
            "id": "7tFZL1yVpfLX0Yz4McGRkL",
            "name": "Crazy (Single Mix) - 2022 Remaster",
            "artists": "Seal"
        }
    ],
    [
        {
            "id": "5S5lSRSU4ADVzxBwnr2AwO",
            "name": "Something's Going On",
            "artists": "Lambchop"
        },
        {
            "id": "1sCy1NaGoXRVwy4qwHWYUQ",
            "name": "Sirenesque",
            "artists": "The Bathers"
        },
        {
            "id": "6nV63LhQA2qVdf6D5urX0V",
            "name": "Straight to You",
            "artists": "Nick Cave & The Bad Seeds"
        }
    ],
    [
        {
            "id": "0NN32Knbyo4gM1DKY9rdzg",
            "name": "Do Ya",
            "artists": "Electric Light Orchestra"
        },
        {
            "id": "3qt3ybU6MScMxMKL2TYBvt",
            "name": "No Particular Place To Go",
            "artists": "Chuck Berry"
        },
        {
            "id": "6ZBeRXjadHvBk9VYSnoO0R",
            "name": "You Don't Mess Around with Jim",
            "artists": "Jim Croce"
        }
    ],
    [
        {
            "id": "0cJPLFrlV7TTCyPLupHzcH",
            "name": "Won't Get Fooled Again - Original Album Version",
            "artists": "The Who"
        },
        {
            "id": "7bOYOD0d7ByMTXvJnQVl8d",
            "name": "Maria",
            "artists": "Blondie"
        },
        {
            "id": "79MMMdYL00iwKVHBSAUkLY",
            "name": "I Wanna Be Your Dog - 2019 Remaster",
            "artists": "The Stooges"
        }
    ],
    [
        {
            "id": "5BCykgPXc7zEBg2oU0klvy",
            "name": "Who Can It Be Now?",
            "artists": "Men At Work"
        },
        {
            "id": "2AkmdLbVKS1steeZdy8H1l",
            "name": "I Want To Break Free - Single Remix",
            "artists": "Queen"
        },
        {
            "id": "3FdHgoJbH3DXNtGLh56pFu",
            "name": "Conga!",
            "artists": "Miami Sound Machine"
        }
    ],
    [
        {
            "id": "6xq5DxZWGgdStAxGAil0yw",
            "name": "Since You Been Gone",
            "artists": "Rainbow"
        },
        {
            "id": "67eX1ovaHyVPUinMHeUtIM",
            "name": "Hurts So Good",
            "artists": "John Mellencamp"
        },
        {
            "id": "3zwmW1gM4E8FlHXV5nE16u",
            "name": "Be Yourself",
            "artists": "Audioslave"
        }
    ],
    [
        {
            "id": "3fH4KjXFYMmljxrcGrbPj9",
            "name": "Don't You (Forget About Me)",
            "artists": "Simple Minds"
        },
        {
            "id": "2UKkLqST2xWpK8n1b0Xr5Z",
            "name": "Return To Innocence",
            "artists": "Enigma"
        },
        {
            "id": "79FPdsekcDp7RWK1IzClbr",
            "name": "Human",
            "artists": "The Human League"
        }
    ],
    [
        {
            "id": "3aphjIiJKa139JSLzXWZHB",
            "name": "Sign Your Name",
            "artists": "Sananda Maitreya"
        },
        {
            "id": "1kdhASMTLoYBCSnmBat6gF",
            "name": "Your Love",
            "artists": "Margaret Urlich"
        },
        {
            "id": "3i4Kxx9CgV9QOAehqpgkuB",
            "name": "My Obsession",
            "artists": "ICEHOUSE"
        }
    ],
    [
        {
            "id": "6mYrhCAGWzTdF8QnKuchXM",
            "name": "If I Could Turn Back Time",
            "artists": "Cher"
        },
        {
            "id": "23IJ5wLRhEZ9DOuia5mPiZ",
            "name": "Who Are You",
            "artists": "The Who"
        },
        {
            "id": "1Vp8U39YNsDfd6yVuaUq12",
            "name": "Atlantic City",
            "artists": "Bruce Springsteen"
        }
    ],
    [
        {
            "id": "7e89621JPkKaeDSTQ3avtg",
            "name": "Sweet Home Alabama",
            "artists": "Lynyrd Skynyrd"
        },
        {
            "id": "7o7E1nrHWncYY7PY94gCiX",
            "name": "Video Killed The Radio Star",
            "artists": "The Buggles"
        },
        {
            "id": "3pVj1Dpgf45D4yCG7w8f6M",
            "name": "The Final Countdown",
            "artists": "Europe"
        }
    ],
    [
        {
            "id": "5g7sDjBhZ4I3gcFIpkrLuI",
            "name": "Locked out of Heaven",
            "artists": "Bruno Mars"
        },
        {
            "id": "6xE6ZWzK1YDDSYzqOCoQlz",
            "name": "Last Train to London",
            "artists": "Electric Light Orchestra"
        },
        {
            "id": "2v7ywbUzCgcVohHaKUcacV",
            "name": "Like a Prayer",
            "artists": "Madonna"
        }
    ],
    [
        {
            "id": "0jvN7eQJJt4nxQzgQfZ1SP",
            "name": "Spirit In The Sky - Deluxe Edition",
            "artists": "Norman Greenbaum"
        },
        {
            "id": "4BVE5tIIpYabZcYCbephNW",
            "name": "Touch Me",
            "artists": "The Doors"
        },
        {
            "id": "0LrwgdLsFaWh9VXIjBRe8t",
            "name": "Changes - 2015 Remaster",
            "artists": "David Bowie"
        }
    ],
    [
        {
            "id": "0e3yhVeNaTfKIWQRw9U9sY",
            "name": "Sacrifice",
            "artists": "Elton John"
        },
        {
            "id": "4OwHGqPeImnNC8F44NcJ3j",
            "name": "The Grease Mega-Mix - From \"Grease\"",
            "artists": "John Travolta"
        },
        {
            "id": "3X7uFMzJrEE0sxn62qd8Ch",
            "name": "Nothing's Gonna Stop Us Now",
            "artists": "Starship"
        }
    ],
    [
        {
            "id": "4HSAJpNocVNJbwbQvtCMdO",
            "name": "Signs",
            "artists": "Snoop Dogg"
        },
        {
            "id": "5mNV8Mz59bzyuQ53gTw0c0",
            "name": "Where the Party At (feat. Nelly)",
            "artists": "Jagged Edge"
        },
        {
            "id": "1mVTQSGoFchL3VVrIa0MeH",
            "name": "Millionaire (feat. André 3000)",
            "artists": "Kelis"
        }
    ],
    [
        {
            "id": "17S4XrLvF5jlGvGCJHgF51",
            "name": "Learning To Fly",
            "artists": "Tom Petty and the Heartbreakers"
        },
        {
            "id": "1oJNFfudxPZ1L4ObketBZK",
            "name": "Throw Your Arms Around Me",
            "artists": "Hunters & Collectors"
        },
        {
            "id": "7snQQk1zcKl8gZ92AnueZW",
            "name": "Sweet Child O' Mine",
            "artists": "Guns N' Roses"
        }
    ],
    [
        {
            "id": "7J1uxwnxfQLu4APicE5Rnj",
            "name": "Billie Jean",
            "artists": "Michael Jackson"
        },
        {
            "id": "3Nf8oGn1okobzjDcFCvT6n",
            "name": "I'll Stand by You",
            "artists": "Pretenders"
        },
        {
            "id": "2yBVeksU2EtrPJbTu4ZslK",
            "name": "What a Fool Believes",
            "artists": "The Doobie Brothers"
        }
    ],
    [
        {
            "id": "2WoUwDID685u7IE1iZ3HUM",
            "name": "If You Leave Me Can I Come Too? - Remastered",
            "artists": "Mental As Anything"
        },
        {
            "id": "3v0oeIduqRtJsaHF1VRmZ2",
            "name": "The Rain In My Heart",
            "artists": "Weddings Parties Anything"
        },
        {
            "id": "0myOYnZ97SgKGUZipzfkRx",
            "name": "Wintercoat",
            "artists": "Paul Kelly"
        }
    ],
    [
        {
            "id": "2gJDyiRxxIglLXp545SPVL",
            "name": "I Knew You Were Waiting (For Me)",
            "artists": "Aretha Franklin"
        },
        {
            "id": "5BckPAYcKEJuYs1eV1BHHe",
            "name": "Take A Chance On Me",
            "artists": "ABBA"
        },
        {
            "id": "07GvNcU1WdyZJq3XxP0kZa",
            "name": "Go Your Own Way - 2004 Remaster",
            "artists": "Fleetwood Mac"
        }
    ],
    [
        {
            "id": "5DuTNKFEjJIySAyJH1yNDU",
            "name": "The Message (feat. Melle Mel & Duke Bootee)",
            "artists": "Grandmaster Flash & The Furious Five"
        },
        {
            "id": "0v9kGNjkKdQUdDoBIuiph4",
            "name": "My Prerogative",
            "artists": "Bobby Brown"
        },
        {
            "id": "4HiC3ulkTgbEcYYsSuR6PO",
            "name": "Danger Zone - From \"Top Gun\" Original Soundtrack",
            "artists": "Kenny Loggins"
        }
    ],
    [
        {
            "id": "6QZ1MctE4g9okI0GjIWEqu",
            "name": "Memory",
            "artists": "Tredegar Town Band"
        },
        {
            "id": "33s5cuB523estLjmR7dH0I",
            "name": "The Bridge on the River Kwai",
            "artists": "Williams Fairey Band"
        },
        {
            "id": "29a7aP0BogynsKvHUoB3he",
            "name": "I Was Made For Loving You",
            "artists": "Desmond Child"
        }
    ],
    [
        {
            "id": "2RH10TTlPhq8S61rXlVssL",
            "name": "You're All I've Got Tonight",
            "artists": "The Cars"
        },
        {
            "id": "2Rn7bVL1FVYboc4c55RUdg",
            "name": "Dreaming",
            "artists": "Blondie"
        },
        {
            "id": "2DEEMhTiUMvkiHFdXkrKfI",
            "name": "Church Of The Poison Mind - Remastered 2002",
            "artists": "Culture Club"
        }
    ],
    [
        {
            "id": "0cJPLFrlV7TTCyPLupHzcH",
            "name": "Won't Get Fooled Again - Original Album Version",
            "artists": "The Who"
        },
        {
            "id": "2Nz6aF1umHh5Et6I5H581L",
            "name": "Hooked On A Feeling",
            "artists": "Blue Swede"
        },
        {
            "id": "0bRNszTbTFLNlunAeh7eom",
            "name": "Sharp Dressed Man (2008 Remaster)",
            "artists": "ZZ Top"
        }
    ],
    [
        {
            "id": "5tORtBzHUAnNrIw5Ql3kHZ",
            "name": "Keep Your Hands to Yourself",
            "artists": "The Georgia Satellites"
        },
        {
            "id": "3pHpV3pa96s4vuBP7sQq0V",
            "name": "Is This Love - 2018 Remaster",
            "artists": "Whitesnake"
        },
        {
            "id": "2JaHGxFJd6R5mwmYTRZS6I",
            "name": "Teacher, Teacher",
            "artists": "38 Special"
        }
    ],
    [
        {
            "id": "0UvCh63URrLFcPkKt99hHd",
            "name": "Don't Look Back in Anger - Remastered",
            "artists": "Oasis"
        },
        {
            "id": "3EYOJ48Et32uATr9ZmLnAo",
            "name": "Roxanne",
            "artists": "The Police"
        },
        {
            "id": "4ReyTz0y3TGkX48wO3Llot",
            "name": "Epic",
            "artists": "Faith No More"
        }
    ],
    [
        {
            "id": "3mJ6pNcFM2CkykCYSREdKT",
            "name": "When I Think Of You",
            "artists": "Janet Jackson"
        },
        {
            "id": "1mCsF9Tw4AkIZOjvZbZZdT",
            "name": "Break My Stride",
            "artists": "Matthew Wilder"
        },
        {
            "id": "5izGeTxueiFX1UPFGohY9w",
            "name": "Addicted To Love",
            "artists": "Robert Palmer"
        }
    ],
    [
        {
            "id": "1ftJRBa7l1Wqh98ox36QeL",
            "name": "Vogue (Single Version) - 2022 Remaster",
            "artists": "Madonna"
        },
        {
            "id": "1fgvJXlcZ7uIddMpqsqw0L",
            "name": "Love Don't Cost a Thing",
            "artists": "Jennifer Lopez"
        },
        {
            "id": "3FdHgoJbH3DXNtGLh56pFu",
            "name": "Conga!",
            "artists": "Miami Sound Machine"
        }
    ],
    [
        {
            "id": "4z7maGZkAonDlXlwo8q69f",
            "name": "Da Ya Think I'm Sexy?",
            "artists": "Rod Stewart"
        },
        {
            "id": "0qxYx4F3vm1AOnfux6dDxP",
            "name": "You Can Call Me Al",
            "artists": "Paul Simon"
        },
        {
            "id": "2XVQdI3m0giGxNrwUhV3yP",
            "name": "Funkytown",
            "artists": "Lipps Inc."
        }
    ],
    [
        {
            "id": "5uCax9HTNlzGybIStD3vDh",
            "name": "Say You Won't Let Go",
            "artists": "James Arthur"
        },
        {
            "id": "0ygAYQQy7bfDN6gH640bbl",
            "name": "Wake Me Up",
            "artists": "Ed Sheeran"
        },
        {
            "id": "5qII2n90lVdPDcgXEEVHNy",
            "name": "Sunday Morning",
            "artists": "Maroon 5"
        }
    ],
    [
        {
            "id": "6nxlHmpBJYicXHC0mvcKOm",
            "name": "Cat Scratch Fever",
            "artists": "Ted Nugent"
        },
        {
            "id": "5N9Cyn5D4Ug7vWcykzlHO2",
            "name": "Foxey Lady",
            "artists": "Jimi Hendrix"
        },
        {
            "id": "6BmzbaB08O0FjHXeS0cR5b",
            "name": "Dancing In The Moonlight (It's Caught Me In It's Spotlight)",
            "artists": "Thin Lizzy"
        }
    ],
    [
        {
            "id": "12VzulX6U34ea0LXm6zGGf",
            "name": "Predictable",
            "artists": "Delta Goodrem"
        },
        {
            "id": "2MGZFL6kqsXxXojlm64BUn",
            "name": "True Blue",
            "artists": "John Williamson"
        },
        {
            "id": "2tm9W2XJxqdiijxkgLGrCl",
            "name": "Why Does Love Do This To Me",
            "artists": "The Exponents"
        }
    ],
    [
        {
            "id": "6y1dAh36eeJHCfD0Zo3ETg",
            "name": "It's Not Over ('Til it's Over) - Rerecorded",
            "artists": "Starship"
        },
        {
            "id": "3EvpaRZkKWxsgDIO2zMH7g",
            "name": "Heaven Is A Place On Earth - Promo 7\" Edit",
            "artists": "Belinda Carlisle"
        },
        {
            "id": "5tVA6TkbaAH9QMITTQRrNv",
            "name": "Free Fallin'",
            "artists": "Tom Petty"
        }
    ],
    [
        {
            "id": "23IK8TF2MSiLnuEjaYPfVV",
            "name": "Nightshift",
            "artists": "Commodores"
        },
        {
            "id": "62ubbkWAhTOftwgRjHS1UH",
            "name": "All Night Long",
            "artists": "Mary Jane Girls"
        },
        {
            "id": "0W8MpnhaImy0oPRkVpRvjI",
            "name": "I Know You, I Live You",
            "artists": "Chaka Khan"
        }
    ],
    [
        {
            "id": "0y7EXQeOAiklIW66pC03b1",
            "name": "Change His Ways",
            "artists": "Robert Palmer"
        },
        {
            "id": "7odSuL5YY6LBWx3HgktAJ5",
            "name": "Find My Love (feat. Eddi Reader)",
            "artists": "Fairground Attraction"
        },
        {
            "id": "3XGnQzrcKETtHKxpxmEODD",
            "name": "As Hard as It Is",
            "artists": "Fine Young Cannibals"
        }
    ],
    [
        {
            "id": "4T0sfDjQHKwrGQU5LUwskq",
            "name": "Never Again",
            "artists": "Classix Nouveaux"
        },
        {
            "id": "1b2IHNs8Rzo2ICibUoA1G1",
            "name": "Show Me",
            "artists": "ABC"
        },
        {
            "id": "3TBRJsLCcwroEkA3tD4u2N",
            "name": "Der Kommissar",
            "artists": "Falco"
        }
    ],
    [
        {
            "id": "4mGW1OHeFGwd1ThNqQLjUp",
            "name": "Disease - 2007 Remaster",
            "artists": "Matchbox Twenty"
        },
        {
            "id": "373kL6gycElmvrcrnL9tOa",
            "name": "Stacy's Mom",
            "artists": "Bowling For Soup"
        },
        {
            "id": "62nQ8UZVqR2RMvkJHkcO2o",
            "name": "Jeremy",
            "artists": "Pearl Jam"
        }
    ],
    [
        {
            "id": "7jTigeIM01cZ92caGJESF0",
            "name": "Car Wash - Single Version",
            "artists": "Rose Royce"
        },
        {
            "id": "7gaQtc0vrSpmRJpSMDiPEk",
            "name": "All Night Long (All Night)",
            "artists": "Lionel Richie"
        },
        {
            "id": "7FwBtcecmlpc1sLySPXeGE",
            "name": "Dancing In the Dark",
            "artists": "Bruce Springsteen"
        }
    ],
    [
        {
            "id": "2JvPJ8ydPuN2NhpH4oti6I",
            "name": "Dance Hall Days",
            "artists": "Wang Chung"
        },
        {
            "id": "3wtMkvedoWMQ3XTKv7tqcZ",
            "name": "Love Is The Drug",
            "artists": "Roxy Music"
        },
        {
            "id": "6wP0zUocK5kGLaBYhLbzt5",
            "name": "Hey Nineteen",
            "artists": "Steely Dan"
        }
    ],
    [
        {
            "id": "4e80zUwo7YuhNHs9OokSG0",
            "name": "Can't Stop This Thing We Started",
            "artists": "Bryan Adams"
        },
        {
            "id": "5K09WxKdlkroDyEVyOSySy",
            "name": "(You Make Me Feel Like) A Natural Woman",
            "artists": "Aretha Franklin"
        },
        {
            "id": "0IWtEFQBwRHaMXZQtGEVcM",
            "name": "Wonderful Life",
            "artists": "Black"
        }
    ],
    [
        {
            "id": "4ugW3mfHisneMpF9q6s3lw",
            "name": "DJ's In A Row - Radio Edit",
            "artists": "Schwab"
        },
        {
            "id": "7rcWgxIVJyQDPLeS1NhnXh",
            "name": "The Fun Lovin' Criminal",
            "artists": "Fun Lovin' Criminals"
        },
        {
            "id": "6x4tKaOzfNJpEJHySoiJcs",
            "name": "Mambo No. 5 (a Little Bit of...)",
            "artists": "Lou Bega"
        }
    ],
    [
        {
            "id": "67iAlVNDDdddxqSD2EZhFs",
            "name": "I'm Gonna Be (500 Miles)",
            "artists": "The Proclaimers"
        },
        {
            "id": "4EhkMUdkAVAsfsjbWU6PPr",
            "name": "Manic Monday",
            "artists": "The Bangles"
        },
        {
            "id": "7HKez549fwJQDzx3zLjHKC",
            "name": "Start Me Up - Remastered 2009",
            "artists": "The Rolling Stones"
        }
    ],
    [
        {
            "id": "0O45fw2L5vsWpdsOdXwNAR",
            "name": "SexyBack (feat. Timbaland)",
            "artists": "Justin Timberlake"
        },
        {
            "id": "3P50dC4GwZYiToIXQGWIAC",
            "name": "Move Over",
            "artists": "Spice Girls"
        },
        {
            "id": "0qV1eEYdqH4UIhxIEabinN",
            "name": "Miss a Thing",
            "artists": "Kylie Minogue"
        }
    ],
    [
        {
            "id": "4QlzkaRHtU8gAdwqjWmO8n",
            "name": "Friday I'm In Love",
            "artists": "The Cure"
        },
        {
            "id": "5J0aNEUTxJWKXnQmyY3vUp",
            "name": "Gypsy - 2016 Remaster",
            "artists": "Fleetwood Mac"
        },
        {
            "id": "2zFdsAIk9r2Mi7Lmm1w3sM",
            "name": "That's All - 2007 Remaster",
            "artists": "Genesis"
        }
    ],
    [
        {
            "id": "4qgZs0RNjdzKAS22lP0QjY",
            "name": "Where The Streets Have No Name - Remastered",
            "artists": "U2"
        },
        {
            "id": "67iAlVNDDdddxqSD2EZhFs",
            "name": "I'm Gonna Be (500 Miles)",
            "artists": "The Proclaimers"
        },
        {
            "id": "1c9dnQbOzw01ID7X2IsYOE",
            "name": "Slave To Love",
            "artists": "Bryan Ferry"
        }
    ],
    [
        {
            "id": "10nyNJ6zNy2YVYLrcwLccB",
            "name": "No Surprises",
            "artists": "Radiohead"
        },
        {
            "id": "42gzADgUU7e2yu5Qn8WfeC",
            "name": "Please Please Please Let Me Get What I Want - 2005 Remaster",
            "artists": "Deftones"
        },
        {
            "id": "5JyJsAZyLTD7W5oWLeB0JK",
            "name": "PPP",
            "artists": "Beach House"
        }
    ],
    [
        {
            "id": "5f2TWu6R2YYCJtLQ0fP78H",
            "name": "Friend Like Me",
            "artists": "Will Smith"
        },
        {
            "id": "1di1BEgJYzPvXUuinsYJGP",
            "name": "Everybody (Backstreet's Back) - Radio Edit",
            "artists": "Backstreet Boys"
        },
        {
            "id": "6KsgCYcZKPcBRDNGhiZWRR",
            "name": "Careless Whisper",
            "artists": "George Michael"
        }
    ],
    [
        {
            "id": "2PuTLcppTOF19G3WOjZRQA",
            "name": "Mucho Mambo (Sway) 2009 - Dj Rebel Radio Edit",
            "artists": "Shaft"
        },
        {
            "id": "3EGI5qmVmGlfgy9BmNb1R8",
            "name": "Lessons In Love",
            "artists": "Level 42"
        },
        {
            "id": "2eGMZhjVlRDcwZERH6savy",
            "name": "Time To Dance - Rocky Piano Remix",
            "artists": "The Shoes"
        }
    ],
    [
        {
            "id": "5hkdfA87RZvNaxl6XiveOA",
            "name": "Everybody's Changing",
            "artists": "Keane"
        },
        {
            "id": "6ADSaE87h8Y3lccZlBJdXH",
            "name": "With Or Without You",
            "artists": "U2"
        },
        {
            "id": "3xkHsmpQCBMytMJNiDf3Ii",
            "name": "Beautiful Things",
            "artists": "Benson Boone"
        }
    ],
    [
        {
            "id": "7tqhbajSfrz2F7E1Z75ASX",
            "name": "Ain't No Mountain High Enough",
            "artists": "Marvin Gaye"
        },
        {
            "id": "43DeSV93pJPT4lCZaWZ6b1",
            "name": "The Boys Are Back In Town",
            "artists": "Thin Lizzy"
        },
        {
            "id": "7gSQv1OHpkIoAdUiRLdmI6",
            "name": "I Won't Back Down",
            "artists": "Tom Petty"
        }
    ],
    [
        {
            "id": "2SzCxX6M6vDwdEwnHDiTaY",
            "name": "Jesus to a Child",
            "artists": "George Michael"
        },
        {
            "id": "5oV1YjM2rtyZ55txHHsFUu",
            "name": "The Shoop Shoop Song (It's In His Kiss)",
            "artists": "Cher"
        },
        {
            "id": "5AM6VOkN7ficA2O04f5JG1",
            "name": "Bad Boy",
            "artists": "Miami Sound Machine"
        }
    ],
    [
        {
            "id": "7gMOe0gXYcELUoVugfMmHP",
            "name": "You May Be Right",
            "artists": "Billy Joel"
        },
        {
            "id": "5xMLcSEstX1jN4arpNXqtX",
            "name": "Na Na Hey Hey Kiss Him Goodbye",
            "artists": "Steam"
        },
        {
            "id": "1L1MWnX8hpdkHWCR4wFk7G",
            "name": "The Loco-Motion",
            "artists": "Kylie Minogue"
        }
    ],
    [
        {
            "id": "4KU75RPjw0m88wKCfkLohA",
            "name": "Whistling Cannonballs",
            "artists": "Shane Nicholson"
        },
        {
            "id": "4L9H7lfXNlLOx1pPs0NwRl",
            "name": "After the Rain",
            "artists": "The Angels"
        },
        {
            "id": "0ANsFaEpaCyv3xzKOH4WDh",
            "name": "Shark Attack",
            "artists": "Split Enz"
        }
    ],
    [
        {
            "id": "3x2ksaXI6EZUWidE2BiLXy",
            "name": "You're Still The One",
            "artists": "Shania Twain"
        },
        {
            "id": "7j31rVgGX9Q2blT92VBEA0",
            "name": "Teenagers",
            "artists": "My Chemical Romance"
        },
        {
            "id": "4JiEyzf0Md7KEFFGWDDdCr",
            "name": "Knockin' On Heaven's Door",
            "artists": "Guns N' Roses"
        }
    ],
    [
        {
            "id": "4sLqcpvMrIJUyOs7x6fl5m",
            "name": "Bloodsport",
            "artists": "Sneaker Pimps"
        },
        {
            "id": "2Q4cjzlPGdjR869Z512sFS",
            "name": "The White Tent the Raft",
            "artists": "Jane Siberry"
        },
        {
            "id": "5mc4CcW3MGzbcheaVSgVXr",
            "name": "Devil Mood",
            "artists": "Smoke City"
        }
    ],
    [
        {
            "id": "2Bs1Lw9LX8hBm70t1iGdlh",
            "name": "He's So Fine - Remastered 2000",
            "artists": "The Chiffons"
        },
        {
            "id": "1CAO7hiNOxJRPW4nFv2aRO",
            "name": "Mama Told Me (Not To Come) - Single Version",
            "artists": "Three Dog Night"
        },
        {
            "id": "13ucj2WfhWBufDKqodpMGz",
            "name": "Shake a Tail Feather",
            "artists": "Ike & Tina Turner"
        }
    ],
    [
        {
            "id": "3ovjw5HZZv43SxTwApooCM",
            "name": "Wind Of Change",
            "artists": "Scorpions"
        },
        {
            "id": "0pQskrTITgmCMyr85tb9qq",
            "name": "Starman - 2012 Remaster",
            "artists": "David Bowie"
        },
        {
            "id": "05wIrZSwuaVWhcv5FfqeH0",
            "name": "Walking On Sunshine",
            "artists": "Katrina & The Waves"
        }
    ],
    [
        {
            "id": "2WfaOiMkCvy7F5fcp2zZ8L",
            "name": "Take on Me",
            "artists": "a-ha"
        },
        {
            "id": "4GhtDORJiSRYxj6M1bv0vX",
            "name": "Love Really Hurts Without You",
            "artists": "Billy Ocean"
        },
        {
            "id": "0UOxp1BpnD8uPQMKU4wKjz",
            "name": "I Shot The Sheriff",
            "artists": "Eric Clapton"
        }
    ],
    [
        {
            "id": "21tuvt3CXIsNquc32v8jpc",
            "name": "Show Me How to Live",
            "artists": "Audioslave"
        },
        {
            "id": "3TW48DvQ7ChwY1Yy1tkMaP",
            "name": "Runaway Train (2022 Remaster)",
            "artists": "Soul Asylum"
        },
        {
            "id": "6wNwHBUjsessjRioNVFbaO",
            "name": "Sour Girl",
            "artists": "Stone Temple Pilots"
        }
    ],
    [
        {
            "id": "4JiEyzf0Md7KEFFGWDDdCr",
            "name": "Knockin' On Heaven's Door",
            "artists": "Guns N' Roses"
        },
        {
            "id": "0Xl2pAlIRE6ANULPdEI7fx",
            "name": "Pink",
            "artists": "Aerosmith"
        },
        {
            "id": "4bO6DljpuAeQh6HS20i0I5",
            "name": "Money For Nothing",
            "artists": "Dire Straits"
        }
    ],
    [
        {
            "id": "6HveTIMynTMzTc5L0TcS20",
            "name": "When You Say Nothing At All",
            "artists": "Alison Krauss & Union Station"
        },
        {
            "id": "09qzRI951OVkXGCc33gzcT",
            "name": "My Maria",
            "artists": "Brooks & Dunn"
        },
        {
            "id": "296XGtH5MeGisqD3uAz6Q6",
            "name": "That's The Way",
            "artists": "Jo Dee Messina"
        }
    ],
    [
        {
            "id": "1gnZ2VCdVUHSgiBKrzdeK8",
            "name": "Monitor",
            "artists": "Siouxsie and the Banshees"
        },
        {
            "id": "4LxNjTEnb4uh1gUg1Y5Ycp",
            "name": "Promises, Promises - US Single Version",
            "artists": "Naked Eyes"
        },
        {
            "id": "3clIHVzJ9J2rvvrFUKLICo",
            "name": "She Bangs the Drums - Remastered 2009",
            "artists": "The Stone Roses"
        }
    ],
    [
        {
            "id": "3j9Ok6kKfYvvZXNxTyoyb7",
            "name": "Prove Your Love",
            "artists": "Taylor Dayne"
        },
        {
            "id": "5p5VhUeL0KrJpIy3s2WaZz",
            "name": "Feels Like I'm In Love (Remastered 2022) (The Lost PWL 12 Mix)",
            "artists": "Kelly Marie"
        },
        {
            "id": "54eGiaQgf3RihFZTUuSMaI",
            "name": "Can't Take My Eyes Off of You",
            "artists": "Tina Charles"
        }
    ],
    [
        {
            "id": "314QzMOrpNUqWBUozYshf6",
            "name": "Buttons",
            "artists": "The Pussycat Dolls"
        },
        {
            "id": "2Ms33RTRCT6gArrpcrPxmo",
            "name": "Feel",
            "artists": "Robbie Williams"
        },
        {
            "id": "0yfNXxlyXdmP0ue1iJijx1",
            "name": "Come Undone",
            "artists": "Duran Duran"
        }
    ],
    [
        {
            "id": "37BTh5g05cxBIRYMbw8g2T",
            "name": "Rosanna",
            "artists": "TOTO"
        },
        {
            "id": "6SMHgPgNkhe9lneNTbgtel",
            "name": "Love and Happiness",
            "artists": "Al Green"
        },
        {
            "id": "0dMd4rilfd6gPbXaLpNYhu",
            "name": "Higher Ground",
            "artists": "Stevie Wonder"
        }
    ],
    [
        {
            "id": "6lV2MSQmRIkycDScNtrBXO",
            "name": "Airplanes (feat. Hayley Williams of Paramore)",
            "artists": "B.o.B"
        },
        {
            "id": "0FYUTxJZvvOVLopuhusqYC",
            "name": "Run The Show (feat. Busta Rhymes)",
            "artists": "Kat Deluna"
        },
        {
            "id": "1ofhfV90EnYhEr7Un2fWiv",
            "name": "Changes",
            "artists": "2Pac"
        }
    ],
    [
        {
            "id": "7snQQk1zcKl8gZ92AnueZW",
            "name": "Sweet Child O' Mine",
            "artists": "Guns N' Roses"
        },
        {
            "id": "7j74lucZ59vqN67Ipe2ZcY",
            "name": "Maneater",
            "artists": "Daryl Hall & John Oates"
        },
        {
            "id": "5LxvwujISqiB8vpRYv887S",
            "name": "I Want You Back",
            "artists": "The Jackson 5"
        }
    ],
    [
        {
            "id": "0ozd432IdkUR3ItM8ieKt0",
            "name": "Point of No Return",
            "artists": "Exposé"
        },
        {
            "id": "7o7E1nrHWncYY7PY94gCiX",
            "name": "Video Killed The Radio Star",
            "artists": "The Buggles"
        },
        {
            "id": "4YOJFyjqh8eAcbKFfv88mV",
            "name": "Y.M.C.A.",
            "artists": "Village People"
        }
    ],
    [
        {
            "id": "63G27PTar9LZQgKU2BKjx9",
            "name": "The Universal - 2012 Remaster",
            "artists": "Blur"
        },
        {
            "id": "7HKez549fwJQDzx3zLjHKC",
            "name": "Start Me Up - Remastered 2009",
            "artists": "The Rolling Stones"
        },
        {
            "id": "21rz5LMBiIpQWRGQcb0xIg",
            "name": "Pretty Vacant",
            "artists": "Sex Pistols"
        }
    ],
    [
        {
            "id": "6KIS5YIZAyeiFNx1aE1OhY",
            "name": "Hang on to Your Love",
            "artists": "Sade"
        },
        {
            "id": "754kgU5rWscRTfvlsuEwFp",
            "name": "Kiss Me",
            "artists": "Sixpence None The Richer"
        },
        {
            "id": "3MtP9T0WF4xbIo8vqHYeXM",
            "name": "Spooky",
            "artists": "Dusty Springfield"
        }
    ],
    [
        {
            "id": "4KfSdst7rW39C0sfhArdrz",
            "name": "Barracuda",
            "artists": "Heart"
        },
        {
            "id": "37gG4GPeTRPKKdXYx3zTRC",
            "name": "Song For The Dead",
            "artists": "Queens of the Stone Age"
        },
        {
            "id": "37Vzad7uGm0I9zJIFXlT4b",
            "name": "Youth Gone Wild",
            "artists": "Skid Row"
        }
    ],
    [
        {
            "id": "5qFxuUIAwJlzO60vqOiL7y",
            "name": "Rainbow In The Dark",
            "artists": "Dio"
        },
        {
            "id": "7fURZRPkB2S70sYR1naKTK",
            "name": "Black Hole Sun",
            "artists": "Soundgarden"
        },
        {
            "id": "4RLIujooyQaBKKLXPB5LnQ",
            "name": "Just Another Victim",
            "artists": "Helmet"
        }
    ],
    [
        {
            "id": "2dpEvh7LQ0ZoUqVXI9unjG",
            "name": "Shadow Of Your Love",
            "artists": "GANGgajang"
        },
        {
            "id": "5tnfrG2numImyYFpsdMa9F",
            "name": "No Lies",
            "artists": "Noiseworks"
        },
        {
            "id": "0wmey5UfcFvYvlp7y0uopE",
            "name": "He's Gonna Step on You Again",
            "artists": "The Party Boys"
        }
    ],
    [
        {
            "id": "2MLHyLy5z5l5YRp7momlgw",
            "name": "Island In The Sun",
            "artists": "Weezer"
        },
        {
            "id": "66ZcOcouenzZEnzTJvoFmH",
            "name": "The Sweet Escape",
            "artists": "Gwen Stefani"
        },
        {
            "id": "7N3PAbqfTjSEU1edb2tY8j",
            "name": "Jump - 2015 Remaster",
            "artists": "Van Halen"
        }
    ],
    [
        {
            "id": "3FlOciKDqFlTMPeC7t92Qy",
            "name": "She Works Hard For The Money",
            "artists": "Donna Summer"
        },
        {
            "id": "6r2BECwMgEoRb5yLfp0Hca",
            "name": "Born This Way",
            "artists": "Lady Gaga"
        },
        {
            "id": "3YqJlngd0Bx4zsqWkkaGSa",
            "name": "Sorry",
            "artists": "Madonna"
        }
    ],
    [
        {
            "id": "5LIQBa14xlboDhAjw4tFaR",
            "name": "It Wasn't Me",
            "artists": "Shaggy"
        },
        {
            "id": "0OXzyIutbMk24FfWmZqrzw",
            "name": "I Say A Little Prayer (with Pharrell Williams)",
            "artists": "Tori Kelly"
        },
        {
            "id": "7BqBn9nzAq8spo5e7cZ0dJ",
            "name": "Just the Way You Are",
            "artists": "Bruno Mars"
        }
    ],
    [
        {
            "id": "1h2xVEoJORqrg71HocgqXd",
            "name": "Superstition - Single Version",
            "artists": "Stevie Wonder"
        },
        {
            "id": "2EqlS6tkEnglzr7tkKAAYD",
            "name": "Come Together - Remastered 2009",
            "artists": "The Beatles"
        },
        {
            "id": "6OnfBiiSc9RGKiBKKtZXgQ",
            "name": "We Built This City",
            "artists": "Starship"
        }
    ]
]